LICENSE
MANIFEST.in
README.md
setup.py
fluke/__init__.py
fluke/apps.py
fluke/filters.py
fluke/fluke.py
fluke/forms.py
fluke/layout.py
fluke/models.py
fluke/sites.py
fluke/util.py
fluke/vendors.py
fluke/widgets.py
fluke/locale/de_DE/LC_MESSAGES/django.mo
fluke/locale/de_DE/LC_MESSAGES/django.po
fluke/locale/de_DE/LC_MESSAGES/djangojs.mo
fluke/locale/de_DE/LC_MESSAGES/djangojs.po
fluke/locale/en/LC_MESSAGES/django.mo
fluke/locale/en/LC_MESSAGES/django.po
fluke/locale/en/LC_MESSAGES/djangojs.mo
fluke/locale/en/LC_MESSAGES/djangojs.po
fluke/locale/es_MX/LC_MESSAGES/django.mo
fluke/locale/es_MX/LC_MESSAGES/django.po
fluke/locale/es_MX/LC_MESSAGES/djangojs.mo
fluke/locale/es_MX/LC_MESSAGES/djangojs.po
fluke/locale/eu/LC_MESSAGES/django.mo
fluke/locale/eu/LC_MESSAGES/django.po
fluke/locale/eu/LC_MESSAGES/djangojs.mo
fluke/locale/eu/LC_MESSAGES/djangojs.po
fluke/locale/id_ID/LC_MESSAGES/django.mo
fluke/locale/id_ID/LC_MESSAGES/django.po
fluke/locale/id_ID/LC_MESSAGES/djangojs.mo
fluke/locale/id_ID/LC_MESSAGES/djangojs.po
fluke/locale/ja/LC_MESSAGES/django.mo
fluke/locale/ja/LC_MESSAGES/django.po
fluke/locale/ja/LC_MESSAGES/djangojs.mo
fluke/locale/ja/LC_MESSAGES/djangojs.po
fluke/locale/lt/LC_MESSAGES/django.mo
fluke/locale/lt/LC_MESSAGES/django.po
fluke/locale/lt/LC_MESSAGES/djangojs.mo
fluke/locale/lt/LC_MESSAGES/djangojs.po
fluke/locale/nl_NL/LC_MESSAGES/django.mo
fluke/locale/nl_NL/LC_MESSAGES/django.po
fluke/locale/nl_NL/LC_MESSAGES/djangojs.mo
fluke/locale/nl_NL/LC_MESSAGES/djangojs.po
fluke/locale/pl/LC_MESSAGES/django.mo
fluke/locale/pl/LC_MESSAGES/django.po
fluke/locale/pl/LC_MESSAGES/djangojs.mo
fluke/locale/pl/LC_MESSAGES/djangojs.po
fluke/locale/pt_BR/LC_MESSAGES/django.mo
fluke/locale/pt_BR/LC_MESSAGES/django.po
fluke/locale/pt_BR/LC_MESSAGES/djangojs.mo
fluke/locale/pt_BR/LC_MESSAGES/djangojs.po
fluke/locale/ru_RU/LC_MESSAGES/django.mo
fluke/locale/ru_RU/LC_MESSAGES/django.po
fluke/locale/ru_RU/LC_MESSAGES/djangojs.mo
fluke_yw.egg-info/PKG-INFO
fluke_yw.egg-info/SOURCES.txt
fluke_yw.egg-info/dependency_links.txt
fluke_yw.egg-info/top_level.txt