Metadata-Version: 2.1
Name: fluke-yw
Version: 0.2.3
Summary: fluke for building website
Home-page: https://github.com/
Author: yan wang
Author-email: 1449349985@qq.com
License: MIT
Classifier: License :: OSI Approved :: MIT License
Classifier: Programming Language :: Python
Classifier: Programming Language :: Python :: 3
Classifier: Programming Language :: Python :: 3.6
Classifier: Programming Language :: Python :: Implementation :: CPython
Classifier: Programming Language :: Python :: Implementation :: PyPy
Requires-Python: >=3.6.0
License-File: LICENSE
